crender.so
minerva_lib-0.0.5.dist-info/WHEEL
minerva_lib-0.0.5.dist-info/METADATA
minerva_lib-0.0.5.dist-info/top_level.txt
minerva_lib-0.0.5.dist-info/RECORD
minerva_lib-0.0.5.dist-info/LICENSE
minerva_lib/render.py
minerva_lib/autosettings.py
minerva_lib/exporting.py
minerva_lib/importing.py
minerva_lib/skimage_inline.py
minerva_lib/client.py
minerva_lib/_version.py
minerva_lib/__init__.py
minerva_lib/util/progress.py
minerva_lib/util/fileutils.py
minerva_lib/util/s3.py
minerva_lib/util/__init__.py
minerva_lib/crender/render.c
minerva_lib/crender/__init__.py
minerva_lib/crender/wrapper.py
