Metadata-Version: 2.1
Name: minerva-lib
Version: 0.0.5
Summary: Minerva Python library
Home-page: https://github.com/sorgerlab/minerva-lib-python
Author: D.P.W. Russell, Juha Ruokonen
Author-email: douglas_russell@hms.harvard.edu, juha_ruokonen@hms.harvard.edu
License: MIT
Download-URL: https://github.com/sorgerlab/minerva-lib-python/archive/v0.0.5.tar.gz
Keywords: minerva,library,microscopy
Platform: UNKNOWN
Classifier: Development Status :: 1 - Planning
Classifier: Intended Audience :: Developers
Classifier: Intended Audience :: Science/Research
Classifier: License :: OSI Approved :: MIT License
Classifier: Natural Language :: English
Classifier: Operating System :: OS Independent
Classifier: Programming Language :: Python :: 3
Classifier: Topic :: Scientific/Engineering :: Visualization
Requires-Python: >=3.7
Requires-Dist: numpy (>=1.18)
Requires-Dist: boto3 (>=1.14.44)
Requires-Dist: botocore (>=1.17.44)
Requires-Dist: requests (==2.22.0)
Requires-Dist: tifffile (>=2020.11.26)
Requires-Dist: importlib-resources
Requires-Dist: s3transfer
Requires-Dist: imagecodecs
Requires-Dist: zarr (==2.6.1)
Requires-Dist: s3fs (==0.4.2)
